aamg.py
aamg-1.1.6.dist-info/METADATA
aamg-1.1.6.dist-info/WHEEL
aamg-1.1.6.dist-info/licenses/LICENSE
aamg-1.1.6.dist-info/RECORD
