Metadata-Version: 2.4
Name: aamg
Version: 1.1.6
Summary: THE Advanced Application Manager Generator or AAMG is a Python library for creating AAMs from A to Z using Python.
Project-URL: Homepage, https://github.com/WeDu-official/AAMG
Project-URL: Issues, https://github.com/WeDu-official/AAMG/issues
Author-email: WeDu-official <fplu.the.founder@gmail.com>
License-File: LICENSE
Classifier: Development Status :: 6 - Mature
Classifier: Intended Audience :: Developers
Classifier: License :: Other/Proprietary License
Classifier: Natural Language :: English
Classifier: Operating System :: Microsoft :: Windows :: Windows 8.1
Classifier: Operating System :: Microsoft :: Windows :: Windows 10
Classifier: Operating System :: Microsoft :: Windows :: Windows 11
Classifier: Programming Language :: Python :: 3.8
Classifier: Programming Language :: Python :: 3.9
Classifier: Programming Language :: Python :: 3.10
Classifier: Programming Language :: Python :: 3.11
Classifier: Programming Language :: Python :: 3.12
Classifier: Programming Language :: Python :: 3.13
Requires-Python: >=3.8
